python_proxy_headers/__init__.py
python_proxy_headers/aiohttp_proxy.py
python_proxy_headers/httpx_proxy.py
python_proxy_headers/requests_adapter.py
python_proxy_headers/urllib3_proxy_manager.py
python_proxy_headers-0.1.0.dist-info/LICENSE
python_proxy_headers-0.1.0.dist-info/METADATA
python_proxy_headers-0.1.0.dist-info/WHEEL
python_proxy_headers-0.1.0.dist-info/top_level.txt
python_proxy_headers-0.1.0.dist-info/RECORD
