Metadata-Version: 2.2
Name: python-proxy-headers
Version: 0.1.0
Summary: Handle custom proxy headers for http requests in various python libraries
Author-email: ProxyMesh <support@proxymesh.com>
Project-URL: Homepage, https://github.com/proxymesh/python-proxy-headers
Project-URL: Changelog, https://github.com/proxymesh/python-proxy-headers/commits/main/
Project-URL: Issues, https://github.com/proxymesh/python-proxy-headers/issues
Classifier: Programming Language :: Python :: 3
Classifier: Operating System :: OS Independent
Classifier: License :: OSI Approved :: BSD License
Classifier: Intended Audience :: Developers
Classifier: Topic :: Internet :: WWW/HTTP
Classifier: Topic :: Software Development :: Libraries :: Python Modules
Requires-Python: >=3.8
License-File: LICENSE
